PA23013UNO/__init__.py
PA23013UNO/ejemplos.py
PA23013UNO/metodos_lineales.py
PA23013UNO/metodos_no_lineales.py
pa23013uno-1.0.0.dist-info/licenses/LICENSE
pa23013uno-1.0.0.dist-info/METADATA
pa23013uno-1.0.0.dist-info/WHEEL
pa23013uno-1.0.0.dist-info/top_level.txt
pa23013uno-1.0.0.dist-info/RECORD
