Metadata-Version: 2.4
Name: PA23013UNO
Version: 1.0.0
Summary: Librería para resolver sistemas de ecuaciones lineales y no lineales.
Author: Emerson Ponce
Classifier: Programming Language :: Python :: 3
Classifier: License :: OSI Approved :: MIT License
Classifier: Operating System :: OS Independent
Requires-Python: >=3.8
License-File: LICENSE
Requires-Dist: numpy
Dynamic: author
Dynamic: classifier
Dynamic: description
Dynamic: description-content-type
Dynamic: license-file
Dynamic: requires-dist
Dynamic: requires-python
Dynamic: summary
